mcp_server_jl/__init__.py
mcp_server_jl/cli.py
mcp_server_jl-0.1.8.dist-info/licenses/LICENSE
mcp_server_jl-0.1.8.dist-info/METADATA
mcp_server_jl-0.1.8.dist-info/WHEEL
mcp_server_jl-0.1.8.dist-info/entry_points.txt
mcp_server_jl-0.1.8.dist-info/top_level.txt
mcp_server_jl-0.1.8.dist-info/RECORD
