Metadata-Version: 2.4
Name: mcp-server-jl
Version: 0.1.8
Summary: Joblogic MCP server using stdio transport
Author-email: Joblogic <support@example.com>
License-Expression: MIT
Project-URL: Homepage, https://github.com/joblogic/mcp-server-jl
Project-URL: Bug Tracker, https://github.com/joblogic/mcp-server-jl/issues
Classifier: Programming Language :: Python :: 3
Classifier: Programming Language :: Python :: 3.12
Classifier: Operating System :: OS Independent
Classifier: Development Status :: 4 - Beta
Classifier: Intended Audience :: Developers
Classifier: Topic :: Software Development :: Libraries :: Python Modules
Requires-Python: >=3.12
License-File: LICENSE
Requires-Dist: anyio>=4.0.0
Requires-Dist: beautifulsoup4>=4.12.3
Requires-Dist: html2text>=2024.2.26
Requires-Dist: mcp[cli]>=1.2.0
Requires-Dist: requests>=2.32.3
Requires-Dist: markitdown>=0.1.0
Dynamic: license-file
